{
  "type": "Feature",
  "properties": {
    "iso:country":"TH",
    "sg:address":"124/113 M.10  Pattaya 3rd Road",
    "sg:city":"Pattaya",
    "sg:classifiers":[
        {
            "category":"Professional",
            "subcategory":"Management & Consulting",
            "type":"Services"
        }
    ],
    "sg:postcode":"20260. ",
    "sg:tags":[
        "bangkok-property",
        "thailand",
        "real-estate-agent",
        "condo",
        "sale",
        "buy",
        "rent"
    ],
    "sg:website":"http://www.soho-properties.com",
    "wof:name":"Soho Properties",
    "wof:placetype":"venue"
},
  "geometry": {"coordinates":[100.882017,12.9327554],"type":"Point"}
}